{
    "type": "AdaptiveCard",
    "$schema": "https://adaptivecards.io/schemas/adaptive-card.json",
    "version": "1.5",
    "body": [
        {
            "type": "TextBlock",
            "text": "Credit limit details",
            "wrap": true,
            "size": "Large",
            "weight": "Bolder"
        },
        {
            "type": "ColumnSet",
            "columns": [
                {
                    "type": "Column",
                    "width": "stretch",
                    "items": [
                        {
                            "type": "TextBlock",
                            "text": "StellarEdge Outdoor Equipment",
                            "wrap": true,
                            "size": "Default",
                            "weight": "Bolder"
                        }
                    ]
                },
                {
                    "type": "Column",
                    "width": "stretch",
                    "items": [
                        {
                            "type": "Badge",
                            "text": "Approved",
                            "size": "ExtraLarge",
                            "style": "Good",
                            "appearance": "Tint",
                            "icon": "CheckmarkCircle",
                            "horizontalAlignment": "Right"
                        }
                    ]
                }
            ]
        },
        {
            "type": "ColumnSet",
            "spacing": "ExtraLarge",
            "columns": [
                {
                    "type": "Column",
                    "width": "auto",
                    "items": [
                        {
                            "type": "TextBlock",
                            "text": "Current Risk Class",
                            "wrap": true,
                            "size": "Small",
                            "weight": "Bolder"
                        },
                        {
                            "type": "ColumnSet",
                            "columns": [
                                {
                                    "type": "Column",
                                    "width": "auto",
                                    "items": [
                                        {
                                            "type": "Icon",
                                            "name": "CheckmarkCircle",
                                            "style": "Filled",
                                            "color": "Good",
                                            "size": "xSmall"
                                        }
                                    ]
                                },
                                {
                                    "type": "Column",
                                    "width": "stretch",
                                    "items": [
                                        {
                                            "type": "TextBlock",
                                            "text": "E (Low Risk)",
                                            "wrap": true,
                                            "spacing": "None",
                                            "size": "Small"
                                        }
                                    ],
                                    "spacing": "ExtraSmall"
                                }
                            ],
                            "spacing": "ExtraSmall"
                        }
                    ],
                    "verticalContentAlignment": "Center"
                },
                {
                    "type": "Column",
                    "width": "auto",
                    "items": [
                        {
                            "type": "TextBlock",
                            "text": "Requested by",
                            "wrap": true,
                            "size": "Small",
                            "weight": "Bolder"
                        },
                        {
                            "type": "ColumnSet",
                            "spacing": "ExtraSmall",
                            "columns": [
                                {
                                    "type": "Column",
                                    "width": "auto",
                                    "items": [
                                        {
                                            "type": "Image",
                                            "url": "https://raw.githubusercontent.com/OfficeDev/Microsoft-Teams-Adaptive-Card-Samples/refs/heads/Suz-ChartReveal/samples/insights/assets/avatar-requestor.png",
                                            "style": "Person",
                                            "size": "Small",
                                            "width": "20px"
                                        }
                                    ]
                                },
                                {
                                    "type": "Column",
                                    "width": "stretch",
                                    "items": [
                                        {
                                            "type": "TextBlock",
                                            "text": "Mark Fullbright",
                                            "wrap": true,
                                            "size": "Small"
                                        }
                                    ],
                                    "spacing": "Small"
                                }
                            ]
                        }
                    ],
                    "verticalContentAlignment": "Center",
                    "spacing": "ExtraLarge"
                },
                {
                    "type": "Column",
                    "width": "auto",
                    "items": [
                        {
                            "type": "TextBlock",
                            "text": "Approvers",
                            "wrap": true,
                            "size": "Small",
                            "weight": "Bolder"
                        },
                        {
                            "type": "ColumnSet",
                            "columns": [
                                {
                                    "type": "Column",
                                    "width": "auto",
                                    "items": [
                                        {
                                            "type": "Image",
                                            "url": "https://raw.githubusercontent.com/OfficeDev/Microsoft-Teams-Adaptive-Card-Samples/refs/heads/Suz-ChartReveal/samples/insights/assets/avatar-approver1.png",
                                            "width": "20px",
                                            "style": "Person"
                                        }
                                    ]
                                },
                                {
                                    "type": "Column",
                                    "width": "auto",
                                    "items": [
                                        {
                                            "type": "Image",
                                            "url": "https://raw.githubusercontent.com/OfficeDev/Microsoft-Teams-Adaptive-Card-Samples/refs/heads/Suz-ChartReveal/samples/insights/assets/avatar-approver2.png",
                                            "width": "20px",
                                            "style": "Person"
                                        }
                                    ],
                                    "spacing": "Small"
                                },
                                {
                                    "type": "Column",
                                    "width": "auto",
                                    "items": [
                                        {
                                            "type": "Image",
                                            "url": "https://raw.githubusercontent.com/OfficeDev/Microsoft-Teams-Adaptive-Card-Samples/refs/heads/Suz-ChartReveal/samples/insights/assets/avatar-approver3.png",
                                            "width": "20px",
                                            "style": "Person"
                                        }
                                    ],
                                    "spacing": "Small"
                                }
                            ],
                            "spacing": "ExtraSmall"
                        }
                    ],
                    "spacing": "ExtraLarge"
                }
            ]
        },
        {
            "type": "TextBlock",
            "text": "Current Credit Management Data",
            "wrap": true,
            "spacing": "ExtraLarge",
            "size": "Small",
            "weight": "Bolder"
        },
        {
            "type": "ColumnSet",
            "columns": [
                {
                    "type": "Column",
                    "width": "stretch",
                    "items": [
                        {
                            "type": "TextBlock",
                            "text": "Current Credit Limit",
                            "wrap": true,
                            "size": "Small",
                            "color": "Default",
                            "isSubtle": true
                        },
                        {
                            "type": "TextBlock",
                            "text": "50.000.000,00 USD",
                            "wrap": true,
                            "spacing": "ExtraSmall",
                            "size": "Small",
                            "weight": "Bolder"
                        }
                    ]
                },
                {
                    "type": "Column",
                    "width": "stretch",
                    "items": [
                        {
                            "type": "TextBlock",
                            "text": "Credit Exposure",
                            "wrap": true,
                            "size": "Small",
                            "color": "Default",
                            "isSubtle": true
                        },
                        {
                            "type": "TextBlock",
                            "text": "34.184.180,40 USD",
                            "wrap": true,
                            "spacing": "ExtraSmall",
                            "size": "Small",
                            "weight": "Bolder"
                        }
                    ]
                },
                {
                    "type": "Column",
                    "width": "stretch",
                    "items": [
                        {
                            "type": "TextBlock",
                            "text": "Limit Utilization",
                            "wrap": true,
                            "size": "Small",
                            "color": "Default",
                            "isSubtle": true
                        },
                        {
                            "type": "TextBlock",
                            "text": "68,4",
                            "wrap": true,
                            "spacing": "ExtraSmall",
                            "size": "Small",
                            "weight": "Bolder"
                        }
                    ]
                }
            ]
        },
        {
            "type": "ActionSet",
            "spacing": "ExtraLarge",
            "actions": [
                {
                    "type": "Action.ShowCard",
                    "title": "Show graphical data",
                    "card": {
                        "$schema": "https://adaptivecards.io/schemas/adaptive-card.json",
                        "type": "AdaptiveCard",
                        "version": "1.5",
                        "body": [
                            {
                                "type": "ColumnSet",
                                "columns": [
                                    {
                                        "type": "Column",
                                        "width": 2,
                                        "items": [
                                            {
                                                "type": "Chart.Line",
                                                "title": "Sample",
                                                "xAxisTitle": "Days",
                                                "yAxisTitle": "Sales",
                                                "data": [
                                                    {
                                                        "legend": "Outlook",
                                                        "values": [
                                                            {
                                                                "x": "2023-05-01",
                                                                "y": 31
                                                            },
                                                            {
                                                                "x": "2023-05-02",
                                                                "y": 72
                                                            },
                                                            {
                                                                "x": "2023-05-03",
                                                                "y": 23
                                                            },
                                                            {
                                                                "x": "2023-05-04",
                                                                "y": 21
                                                            },
                                                            {
                                                                "x": "2023-05-05",
                                                                "y": 39
                                                            },
                                                            {
                                                                "x": "2023-05-06",
                                                                "y": 69
                                                            }
                                                        ]
                                                    },
                                                    {
                                                        "legend": "Teams",
                                                        "values": [
                                                            {
                                                                "x": "2023-05-01",
                                                                "y": 9
                                                            },
                                                            {
                                                                "x": "2023-05-02",
                                                                "y": 15
                                                            },
                                                            {
                                                                "x": "2023-05-03",
                                                                "y": 84
                                                            },
                                                            {
                                                                "x": "2023-05-04",
                                                                "y": 31
                                                            },
                                                            {
                                                                "x": "2023-05-05",
                                                                "y": 55
                                                            },
                                                            {
                                                                "x": "2023-05-06",
                                                                "y": 5
                                                            }
                                                        ]
                                                    }
                                                ]
                                            },
                                            {
                                                "type": "ActionSet",
                                                "actions": [
                                                    {
                                                        "type": "Action.OpenUrl",
                                                        "title": "Open analyzer"
                                                    }
                                                ]
                                            }
                                        ]
                                    },
                                    {
                                        "type": "Column",
                                        "width": 1,
                                        "items": [
                                            {
                                                "type": "Chart.Donut",
                                                "data": [
                                                    {
                                                        "legend": "Outlook",
                                                        "value": 100
                                                    },
                                                    {
                                                        "legend": "Teams",
                                                        "value": 700
                                                    },
                                                    {
                                                        "legend": "Office",
                                                        "value": 1600
                                                    }
                                                ]
                                            }
                                        ]
                                    }
                                ]
                            }
                        ]
                    }
                }
            ]
        }
    ]
}
